{
  "gitSyncId": "685438f5a5632c6893ba4456_596407cb-8dfb-4909-a560-5418668958db",
  "id": "UserManagement_getAllRoles",
  "pluginId": "postgres-plugin",
  "pluginType": "DB",
  "unpublishedAction": {
    "actionConfiguration": {
      "body": "SELECT id, name FROM roles;\n",
      "encodeParamsToggle": true,
      "paginationType": "NONE",
      "pluginSpecifiedTemplates": [
        {
          "value": true
        }
      ],
      "timeoutInMillisecond": 10000
    },
    "confirmBeforeExecute": false,
    "datasource": {
      "id": "neon_inventory_db",
      "isAutoGenerated": false,
      "name": "neon_inventory_db",
      "pluginId": "postgres-plugin"
    },
    "dynamicBindingPathList": [],
    "name": "getAllRoles",
    "pageId": "UserManagement",
    "runBehaviour": "ON_PAGE_LOAD",
    "userSetOnLoad": false
  }
}